{
  "updatedAt": "2026-06-17 02:37",
  "source": "manual",
  "items": {
    "108490": {
      "changePct": -5.42,
      "updatedAt": "2026-06-17 02:37",
      "source": "Naver Finance"
    },
    "277810": {
      "changePct": -6.67,
      "updatedAt": "2026-06-17 02:37",
      "source": "Naver Finance"
    },
    "329180": {
      "changePct": -2.24,
      "updatedAt": "2026-06-17 02:37",
      "source": "Naver Finance"
    },
    "348340": {
      "changePct": -2.61,
      "updatedAt": "2026-06-17 02:37",
      "source": "Naver Finance"
    },
    "389500": {
      "changePct": -3.53,
      "updatedAt": "2026-06-17 02:37",
      "source": "Naver Finance"
    },
    "396500": {
      "changePct": -2.51,
      "updatedAt": "2026-06-17 02:37",
      "source": "Naver Finance"
    },
    "449450": {
      "changePct": 7.97,
      "updatedAt": "2026-06-17 02:37",
      "source": "Naver Finance"
    },
    "454910": {
      "changePct": -2.15,
      "updatedAt": "2026-06-17 02:37",
      "source": "Naver Finance"
    },
    "457480": {
      "changePct": -0.25,
      "updatedAt": "2026-06-17 02:37",
      "source": "Naver Finance"
    },
    "463250": {
      "changePct": 9.51,
      "updatedAt": "2026-06-17 02:37",
      "source": "Naver Finance"
    },
    "465580": {
      "changePct": 1.02,
      "updatedAt": "2026-06-17 02:37",
      "source": "Naver Finance"
    },
    "466920": {
      "changePct": 0.98,
      "updatedAt": "2026-06-17 02:37",
      "source": "Naver Finance"
    },
    "472170": {
      "changePct": 0.73,
      "updatedAt": "2026-06-17 02:37",
      "source": "Naver Finance"
    },
    "485540": {
      "changePct": 0.95,
      "updatedAt": "2026-06-17 02:37",
      "source": "Naver Finance"
    },
    "486450": {
      "changePct": 0.29,
      "updatedAt": "2026-06-17 02:37",
      "source": "Naver Finance"
    },
    "487240": {
      "changePct": 0.2,
      "updatedAt": "2026-06-17 02:37",
      "source": "Naver Finance"
    },
    "494670": {
      "changePct": 1.92,
      "updatedAt": "2026-06-17 02:37",
      "source": "Naver Finance"
    },
    "AVGO": {
      "changePct": -3.8406863989440003,
      "updatedAt": "2026-06-17 02:37",
      "source": "Yahoo Finance"
    },
    "0080G0": {
      "changePct": 9.05,
      "updatedAt": "2026-06-17 02:37",
      "source": "Naver Finance"
    },
    "081660": {
      "changePct": -3.66,
      "updatedAt": "2026-06-17 02:37",
      "source": "Naver Finance"
    },
    "009150": {
      "changePct": 2.45,
      "updatedAt": "2026-06-17 02:37",
      "source": "Naver Finance"
    },
    "MSFT": {
      "changePct": -2.077496497898741,
      "updatedAt": "2026-06-17 02:37",
      "source": "Yahoo Finance"
    },
    "GOOGL": {
      "changePct": 0.4846351698930455,
      "updatedAt": "2026-06-17 02:37",
      "source": "Yahoo Finance"
    },
    "000660": {
      "changePct": 4.11,
      "updatedAt": "2026-06-17 02:37",
      "source": "Naver Finance"
    },
    "AMZN": {
      "changePct": -0.149128189291222,
      "updatedAt": "2026-06-17 02:37",
      "source": "Yahoo Finance"
    },
    "005930": {
      "changePct": 1.78,
      "updatedAt": "2026-06-17 02:37",
      "source": "Naver Finance"
    },
    "NVDA": {
      "changePct": -1.5627206401506204,
      "updatedAt": "2026-06-17 02:37",
      "source": "Yahoo Finance"
    },
    "0155M0": {
      "changePct": 0.89,
      "updatedAt": "2026-06-17 02:37",
      "source": "Naver Finance"
    },
    "017670": {
      "changePct": -5.03,
      "updatedAt": "2026-06-17 02:37",
      "source": "Naver Finance"
    },
    "PLTR": {
      "changePct": -2.939648133026507,
      "updatedAt": "2026-06-17 02:37",
      "source": "Yahoo Finance"
    },
    "NOW": {
      "changePct": -2.573211713874226,
      "updatedAt": "2026-06-17 02:37",
      "source": "Yahoo Finance"
    },
    "TSLA": {
      "changePct": -1.8849568284081237,
      "updatedAt": "2026-06-17 02:37",
      "source": "Yahoo Finance"
    },
    "009540": {
      "changePct": 3.91,
      "updatedAt": "2026-06-17 02:37",
      "source": "Naver Finance"
    },
    "042660": {
      "changePct": 4.7,
      "updatedAt": "2026-06-17 02:37",
      "source": "Naver Finance"
    },
    "010140": {
      "changePct": -1.92,
      "updatedAt": "2026-06-17 02:37",
      "source": "Naver Finance"
    },
    "0115D0": {
      "changePct": 1,
      "updatedAt": "2026-06-17 02:37",
      "source": "Naver Finance"
    },
    "COHR": {
      "changePct": -5.476754301179191,
      "updatedAt": "2026-06-17 02:37",
      "source": "Yahoo Finance"
    },
    "CIEN": {
      "changePct": -6.6765930817202905,
      "updatedAt": "2026-06-17 02:37",
      "source": "Yahoo Finance"
    },
    "LITE": {
      "changePct": -8.321319627261708,
      "updatedAt": "2026-06-17 02:37",
      "source": "Yahoo Finance"
    },
    "GLW": {
      "changePct": -4.460293804556097,
      "updatedAt": "2026-06-17 02:37",
      "source": "Yahoo Finance"
    },
    "MRVL": {
      "changePct": -5.688293188293186,
      "updatedAt": "2026-06-17 02:37",
      "source": "Yahoo Finance"
    },
    "001040": {
      "changePct": 7.17,
      "updatedAt": "2026-06-17 02:37",
      "source": "Naver Finance"
    },
    "058610": {
      "changePct": -0.71,
      "updatedAt": "2026-06-17 02:37",
      "source": "Naver Finance"
    },
    "RKLB": {
      "changePct": -2.942791762013733,
      "updatedAt": "2026-06-17 02:37",
      "source": "Yahoo Finance"
    },
    "ASTS": {
      "changePct": -5.3614251455978,
      "updatedAt": "2026-06-17 02:37",
      "source": "Yahoo Finance"
    },
    "RDW": {
      "changePct": -6.837491571139577,
      "updatedAt": "2026-06-17 02:37",
      "source": "Yahoo Finance"
    },
    "PL": {
      "changePct": -9.287115761935906,
      "updatedAt": "2026-06-17 02:37",
      "source": "Yahoo Finance"
    },
    "CRWV": {
      "changePct": 9.961578108893272,
      "updatedAt": "2026-06-17 02:37",
      "source": "Yahoo Finance"
    },
    "NBIS": {
      "changePct": 3.766293690160347,
      "updatedAt": "2026-06-17 02:37",
      "source": "Yahoo Finance"
    },
    "IREN": {
      "changePct": 0.9202958093672886,
      "updatedAt": "2026-06-17 02:37",
      "source": "Yahoo Finance"
    },
    "HUT": {
      "changePct": 2.021967049425855,
      "updatedAt": "2026-06-17 02:37",
      "source": "Yahoo Finance"
    },
    "TSLL": {
      "changePct": -3.7077033837293056,
      "updatedAt": "2026-06-17 02:37",
      "source": "Yahoo Finance"
    },
    "TEM": {
      "changePct": -1.1276758409785999,
      "updatedAt": "2026-06-17 02:37",
      "source": "Yahoo Finance"
    },
    "0131V0": {
      "changePct": 0.44,
      "updatedAt": "2026-06-17 02:37",
      "source": "Naver Finance"
    },
    "NFLX": {
      "changePct": -4.144728786580146,
      "updatedAt": "2026-06-17 02:37",
      "source": "Yahoo Finance"
    },
    "AAPL": {
      "changePct": 1.217866540719235,
      "updatedAt": "2026-06-17 02:37",
      "source": "Yahoo Finance"
    },
    "SBUX": {
      "changePct": -0.009843488532340896,
      "updatedAt": "2026-06-17 02:37",
      "source": "Yahoo Finance"
    },
    "DIS": {
      "changePct": -0.4769397187530725,
      "updatedAt": "2026-06-17 02:37",
      "source": "Yahoo Finance"
    },
    "NKE": {
      "changePct": 0.5641592920353882,
      "updatedAt": "2026-06-17 02:37",
      "source": "Yahoo Finance"
    },
    "BYND": {
      "changePct": -0.5698005698005704,
      "updatedAt": "2026-06-17 02:37",
      "source": "Yahoo Finance"
    },
    "QQQ": {
      "changePct": -1.5040322580645236,
      "updatedAt": "2026-06-17 02:37",
      "source": "Yahoo Finance"
    },
    "VOO": {
      "changePct": -0.3704077367654973,
      "updatedAt": "2026-06-17 02:37",
      "source": "Yahoo Finance"
    },
    "ETN": {
      "changePct": 1.1656758217461811,
      "updatedAt": "2026-06-17 02:37",
      "source": "Yahoo Finance"
    },
    "SU.PA": {
      "changePct": 2.517120118452716,
      "updatedAt": "2026-06-17 02:37",
      "source": "Yahoo Finance"
    },
    "VRT": {
      "changePct": -1.5452184785047907,
      "updatedAt": "2026-06-17 02:37",
      "source": "Yahoo Finance"
    },
    "GEV": {
      "changePct": 2.529200772555872,
      "updatedAt": "2026-06-17 02:37",
      "source": "Yahoo Finance"
    },
    "ENR.DE": {
      "changePct": -0.05121638924454808,
      "updatedAt": "2026-06-17 02:37",
      "source": "Yahoo Finance"
    },
    "7011.T": {
      "changePct": 4.126810603990162,
      "updatedAt": "2026-06-17 02:37",
      "source": "Yahoo Finance"
    },
    "MU": {
      "changePct": -4.343789924539747,
      "updatedAt": "2026-06-17 02:37",
      "source": "Yahoo Finance"
    },
    "FN": {
      "changePct": -5.866295352276673,
      "updatedAt": "2026-06-17 02:37",
      "source": "Yahoo Finance"
    },
    "CLS": {
      "changePct": -3.5865658693766194,
      "updatedAt": "2026-06-17 02:37",
      "source": "Yahoo Finance"
    },
    "SIVE.ST": {
      "changePct": 7.180081065431388,
      "updatedAt": "2026-06-17 02:37",
      "source": "Yahoo Finance"
    },
    "IQE.L": {
      "changePct": -2.9982363315696694,
      "updatedAt": "2026-06-17 02:37",
      "source": "Yahoo Finance"
    },
    "AXTI": {
      "changePct": -12.190716994762507,
      "updatedAt": "2026-06-17 02:37",
      "source": "Yahoo Finance"
    },
    "5802.T": {
      "changePct": 6.851691240242845,
      "updatedAt": "2026-06-17 02:37",
      "source": "Yahoo Finance"
    },
    "5016.T": {
      "changePct": 18.587360594795538,
      "updatedAt": "2026-06-17 02:37",
      "source": "Yahoo Finance"
    },
    "ORCL": {
      "changePct": -1.8298380398670981,
      "updatedAt": "2026-06-17 02:37",
      "source": "Yahoo Finance"
    },
    "MP": {
      "changePct": -1.3817370408513556,
      "updatedAt": "2026-06-17 02:37",
      "source": "Yahoo Finance"
    },
    "LYC.AX": {
      "changePct": 0.5592841163311042,
      "updatedAt": "2026-06-17 02:37",
      "source": "Yahoo Finance"
    },
    "NEO.TO": {
      "changePct": -1.0814814814814875,
      "updatedAt": "2026-06-17 02:37",
      "source": "Yahoo Finance"
    },
    "META": {
      "changePct": 0.41450427984094435,
      "updatedAt": "2026-06-17 02:37",
      "source": "Yahoo Finance"
    },
    "AMD": {
      "changePct": -5.105434345649224,
      "updatedAt": "2026-06-17 02:37",
      "source": "Yahoo Finance"
    },
    "0981.HK": {
      "changePct": -3.4572733202870265,
      "updatedAt": "2026-06-17 02:37",
      "source": "Yahoo Finance"
    },
    "BABA": {
      "changePct": -2.5855175477565497,
      "updatedAt": "2026-06-17 02:37",
      "source": "Yahoo Finance"
    },
    "0700.HK": {
      "changePct": -2.654482158398617,
      "updatedAt": "2026-06-17 02:37",
      "source": "Yahoo Finance"
    },
    "BIDU": {
      "changePct": -3.605995717344748,
      "updatedAt": "2026-06-17 02:37",
      "source": "Yahoo Finance"
    }
  },
  "errors": []
}
